cruscopoetry/syllabifiers/abstract/__init__.py
cruscopoetry/syllabifiers/abstract/abstract_classes.py
cruscopoetry/syllabifiers/abstract/abstract_tokenizer.py
cruscopoetry/syllabifiers/abstract/exceptions.py
cruscopoetry/syllabifiers/abstract/markers.py
syllabifiers/abstract/__init__.py
syllabifiers/abstract/abstract_classes.py
syllabifiers/abstract/abstract_tokenizer.py
syllabifiers/abstract/exceptions.py
syllabifiers/abstract/markers.py
cruscopoetry.syllabifiers.abstract-0.0.3.dist-info/METADATA
cruscopoetry.syllabifiers.abstract-0.0.3.dist-info/WHEEL
cruscopoetry.syllabifiers.abstract-0.0.3.dist-info/top_level.txt
cruscopoetry.syllabifiers.abstract-0.0.3.dist-info/RECORD
